punicalab_core/__init__.py
punicalab_core/enums/__init__.py
punicalab_core/enums/status_enum.py
punicalab_core/utils/__init__.py
punicalab_core/utils/enum_utils.py
punicalab_core-0.1.0.dist-info/LICENSE
punicalab_core-0.1.0.dist-info/METADATA
punicalab_core-0.1.0.dist-info/WHEEL
punicalab_core-0.1.0.dist-info/top_level.txt
punicalab_core-0.1.0.dist-info/RECORD
