Metadata-Version: 2.1
Name: punicalab-core
Version: 0.1.0
Summary: A Python SDK for managing Status ENUMs and utilities.
Home-page: https://github.com/punicaLab-fuzeAI/punicalab_core
Author: punicalab
Author-email: duzgun.ilaslan@punicalab.com
License: UNKNOWN
Platform: UNKNOWN
Classifier: Programming Language :: Python :: 3
Classifier: License :: OSI Approved :: MIT License
Classifier: Operating System :: OS Independent
Requires-Python: >=3.6
License-File: LICENSE
